[{"job_title":"Customer Configuration Liaison","supervisor":"Mayert","first_name":"Kaelyn","last_name":"Quitzon","work_email":"Oceane_Moen22@gmail.com","addressStreet":"690 Waelchi Corners","addressCity":"East Roderickborough","addressState":"California","addressZip":"38723-1214","dept_id":95625},{"job_title":"National Quality Producer","supervisor":"Huels","first_name":"Austin","last_name":"Bradtke","work_email":"Destinee92@hotmail.com","addressStreet":"1034 Hudson Port","addressCity":"Port Leonardobury","addressState":"Texas","addressZip":"06770-7969","dept_id":47114},{"job_title":"Legacy Paradigm Associate","supervisor":"Feest","first_name":"Abagail","last_name":"Pouros","work_email":"Flavie_Hermann@hotmail.com","addressStreet":"5684 Howard Port","addressCity":"Port Chelsey","addressState":"Arkansas","addressZip":"97407","dept_id":93310},{"job_title":"Dynamic Branding Orchestrator","supervisor":"Bednar","first_name":"Justus","last_name":"Lockman","work_email":"Noel29@gmail.com","addressStreet":"0716 Wiegand Causeway","addressCity":"North Mariah","addressState":"Ohio","addressZip":"11286-6140","dept_id":82838},{"job_title":"Dynamic Accounts Analyst","supervisor":"Fahey","first_name":"Johnpaul","last_name":"Schaden","work_email":"Jettie.Thompson@gmail.com","addressStreet":"8409 Pfannerstill Mountains","addressCity":"North Damian","addressState":"Nebraska","addressZip":"45102","dept_id":63852},{"job_title":"Investor Quality Associate","supervisor":"Murazik","first_name":"Johnson","last_name":"Mills","work_email":"Wilber.DuBuque6@yahoo.com","addressStreet":"1183 Alison Center","addressCity":"Lake Jeromebury","addressState":"Louisiana","addressZip":"59732","dept_id":59229},{"job_title":"Investor Paradigm Associate","supervisor":"Glover","first_name":"Kaycee","last_name":"Nicolas","work_email":"Jevon.Nikolaus88@gmail.com","addressStreet":"18449 Jenkins Track","addressCity":"North Karltown","addressState":"New Hampshire","addressZip":"60884-5528","dept_id":67935},{"job_title":"Human Data Analyst","supervisor":"Hammes","first_name":"Jada","last_name":"Wiegand","work_email":"Johan53@yahoo.com","addressStreet":"30006 Ashlee Estate","addressCity":"West Rutheside","addressState":"New Jersey","addressZip":"51863-7660","dept_id":27562},{"job_title":"Dynamic Functionality Analyst","supervisor":"Carroll","first_name":"Weston","last_name":"Swift","work_email":"Estefania.Mills@yahoo.com","addressStreet":"2149 Kiarra Islands","addressCity":"Smithamton","addressState":"Missouri","addressZip":"85481","dept_id":16138},{"job_title":"International Integration Officer","supervisor":"Adams","first_name":"Theodora","last_name":"Dickens","work_email":"Annette_Shanahan55@gmail.com","addressStreet":"96443 Jazmyne Unions","addressCity":"Farrellton","addressState":"Indiana","addressZip":"44268-9568","dept_id":73141},{"job_title":"Legacy Markets Representative","supervisor":"O'Reilly","first_name":"Elvie","last_name":"Ledner","work_email":"Lafayette.Leffler@hotmail.com","addressStreet":"256 Christopher Unions","addressCity":"East Reynoldshire","addressState":"Iowa","addressZip":"68565-5752","dept_id":88114},{"job_title":"Lead Tactics Associate","supervisor":"Yundt","first_name":"Woodrow","last_name":"Wiegand","work_email":"Aniya_Sauer@gmail.com","addressStreet":"1581 Prohaska Ways","addressCity":"Enricotown","addressState":"Hawaii","addressZip":"82438-2173","dept_id":82116},{"job_title":"Investor Quality Representative","supervisor":"Gulgowski","first_name":"Mina","last_name":"Lind","work_email":"Montana94@hotmail.com","addressStreet":"3867 Mohamed Plaza","addressCity":"West Mustafa","addressState":"Washington","addressZip":"80168-5653","dept_id":73082},{"job_title":"Customer Brand Supervisor","supervisor":"Ratke","first_name":"Donato","last_name":"Feil","work_email":"Ava_Kessler@gmail.com","addressStreet":"49992 Ansley Courts","addressCity":"North Romanview","addressState":"Nebraska","addressZip":"14225","dept_id":41005},{"job_title":"Principal Interactions Consultant","supervisor":"Bruen","first_name":"Rita","last_name":"Padberg","work_email":"Karianne_Pagac@gmail.com","addressStreet":"850 Bogisich Coves","addressCity":"Smithamville","addressState":"North Carolina","addressZip":"96377","dept_id":4250},{"job_title":"Direct Web Producer","supervisor":"Hackett","first_name":"Fern","last_name":"Nienow","work_email":"Conner_Streich@yahoo.com","addressStreet":"815 Maud Keys","addressCity":"Lake Madilyn","addressState":"Delaware","addressZip":"88410-5490","dept_id":57404},{"job_title":"Direct Mobility Administrator","supervisor":"Carter","first_name":"Jonas","last_name":"Gibson","work_email":"Cooper36@hotmail.com","addressStreet":"28328 Leuschke Villages","addressCity":"Madelinefurt","addressState":"Missouri","addressZip":"02265","dept_id":93680},{"job_title":"Lead Web Producer","supervisor":"Will","first_name":"Lewis","last_name":"Gorczany","work_email":"Taya84@yahoo.com","addressStreet":"781 Enos Underpass","addressCity":"Osinskifurt","addressState":"Vermont","addressZip":"92737-1435","dept_id":92324},{"job_title":"Internal Configuration Assistant","supervisor":"Beer","first_name":"Santiago","last_name":"Satterfield","work_email":"Alex.Schaefer@hotmail.com","addressStreet":"40973 Valentin Well","addressCity":"New Ole","addressState":"Ohio","addressZip":"51414-2747","dept_id":63318},{"job_title":"Direct Directives Designer","supervisor":"Dare","first_name":"Joanny","last_name":"Armstrong","work_email":"Keon67@yahoo.com","addressStreet":"42479 Powlowski Bridge","addressCity":"Arnulfoville","addressState":"Montana","addressZip":"28189-7701","dept_id":887},{"job_title":"International Configuration Administrator","supervisor":"Littel","first_name":"Granville","last_name":"Durgan","work_email":"Elwyn_Graham@gmail.com","addressStreet":"77651 Dana Orchard","addressCity":"Keeblerburgh","addressState":"Iowa","addressZip":"96762-7806","dept_id":45542},{"job_title":"Senior Group Planner","supervisor":"White","first_name":"Mia","last_name":"Gleason","work_email":"Maiya51@hotmail.com","addressStreet":"8567 Will Walks","addressCity":"Leopoldborough","addressState":"Illinois","addressZip":"40372","dept_id":42217},{"job_title":"Customer Tactics Facilitator","supervisor":"Smitham","first_name":"Kolby","last_name":"Rau","work_email":"Anabel_Lind@hotmail.com","addressStreet":"259 Walter Wall","addressCity":"Beahanville","addressState":"Connecticut","addressZip":"18856-4605","dept_id":68971},{"job_title":"Central Brand Consultant","supervisor":"Bednar","first_name":"Ross","last_name":"Kohler","work_email":"Otis.Haag@gmail.com","addressStreet":"5916 Keagan Prairie","addressCity":"West Sheridanmouth","addressState":"Idaho","addressZip":"40200","dept_id":89343},{"job_title":"Principal Integration Associate","supervisor":"Hansen","first_name":"Loraine","last_name":"Veum","work_email":"Letitia.Rau34@gmail.com","addressStreet":"266 Schroeder Island","addressCity":"South Micah","addressState":"Louisiana","addressZip":"97358","dept_id":8976},{"job_title":"Global Functionality Planner","supervisor":"Hane","first_name":"Melba","last_name":"Heidenreich","work_email":"Lee44@gmail.com","addressStreet":"411 Magdalena Forge","addressCity":"Kellenport","addressState":"Nevada","addressZip":"30970-0138","dept_id":52042},{"job_title":"Corporate Creative Designer","supervisor":"Tromp","first_name":"Billy","last_name":"Ritchie","work_email":"Walker_Hilll72@gmail.com","addressStreet":"896 Funk Key","addressCity":"Port Jett","addressState":"New York","addressZip":"54285-9996","dept_id":23327},{"job_title":"Regional Communications Analyst","supervisor":"Johns","first_name":"Raul","last_name":"Hermann","work_email":"Darby.Schiller@gmail.com","addressStreet":"841 Schumm Union","addressCity":"Jeramiefurt","addressState":"Virginia","addressZip":"46864","dept_id":52060},{"job_title":"Principal Applications Technician","supervisor":"Larkin","first_name":"Axel","last_name":"Jacobs","work_email":"Caterina.Tromp42@yahoo.com","addressStreet":"801 Douglas Center","addressCity":"Zemlakton","addressState":"Pennsylvania","addressZip":"62961","dept_id":78956},{"job_title":"Forward Creative Supervisor","supervisor":"Batz","first_name":"Maureen","last_name":"Gutkowski","work_email":"Stephanie.Watsica70@hotmail.com","addressStreet":"09212 Roob Extensions","addressCity":"Lake Emmetburgh","addressState":"North Dakota","addressZip":"57237","dept_id":24748},{"job_title":"Legacy Response Designer","supervisor":"Ernser","first_name":"Antonetta","last_name":"Okuneva","work_email":"Jonathon71@gmail.com","addressStreet":"09782 Johathan Springs","addressCity":"East Craigton","addressState":"Texas","addressZip":"62218-4159","dept_id":99757},{"job_title":"Dynamic Group Coordinator","supervisor":"Jones","first_name":"Alan","last_name":"Powlowski","work_email":"Faye_Toy19@gmail.com","addressStreet":"3193 Sandy Course","addressCity":"Caroleside","addressState":"Utah","addressZip":"59136","dept_id":22169},{"job_title":"Internal Solutions Orchestrator","supervisor":"Raynor","first_name":"Santina","last_name":"Larkin","work_email":"Adalberto.Rempel@gmail.com","addressStreet":"4748 McKenzie Station","addressCity":"East Hannahland","addressState":"Minnesota","addressZip":"19468-9867","dept_id":89703},{"job_title":"Future Implementation Analyst","supervisor":"Hoeger","first_name":"Nyasia","last_name":"Veum","work_email":"Hershel60@hotmail.com","addressStreet":"49082 Jones Cape","addressCity":"McKenziefort","addressState":"Florida","addressZip":"86389-6726","dept_id":17290},{"job_title":"Legacy Paradigm Analyst","supervisor":"Hansen","first_name":"Lexus","last_name":"Luettgen","work_email":"Jacques55@yahoo.com","addressStreet":"22952 Alanna Port","addressCity":"Corneliusburgh","addressState":"Michigan","addressZip":"20127","dept_id":75905},{"job_title":"Global Configuration Specialist","supervisor":"Schiller","first_name":"Hilda","last_name":"VonRueden","work_email":"Ocie.Koch@yahoo.com","addressStreet":"3210 Lubowitz Light","addressCity":"Rueckerport","addressState":"Louisiana","addressZip":"95486-8265","dept_id":95000},{"job_title":"International Infrastructure Analyst","supervisor":"Ullrich","first_name":"Vernon","last_name":"Roob","work_email":"Lyric_Murray@gmail.com","addressStreet":"7756 Madalyn Burgs","addressCity":"Leschtown","addressState":"Washington","addressZip":"50765","dept_id":30674},{"job_title":"Dynamic Assurance Assistant","supervisor":"Stoltenberg","first_name":"Dallin","last_name":"Gulgowski","work_email":"Ottilie.Trantow@hotmail.com","addressStreet":"400 Samanta Meadow","addressCity":"New Quinten","addressState":"Colorado","addressZip":"25356-1375","dept_id":18934},{"job_title":"Corporate Operations Strategist","supervisor":"Kassulke","first_name":"Deanna","last_name":"Cronin","work_email":"Amelie_Sanford30@yahoo.com","addressStreet":"5393 O'Hara Turnpike","addressCity":"Purdychester","addressState":"Oklahoma","addressZip":"60752","dept_id":11012},{"job_title":"Product Applications Director","supervisor":"Kessler","first_name":"Krystal","last_name":"Kerluke","work_email":"Kacey.Mills34@gmail.com","addressStreet":"1950 Littel Points","addressCity":"Schambergerhaven","addressState":"Iowa","addressZip":"26331-3845","dept_id":88243},{"job_title":"Legacy Branding Producer","supervisor":"Collier","first_name":"Maximilian","last_name":"Ullrich","work_email":"Samara78@gmail.com","addressStreet":"19965 Harrison Wells","addressCity":"Harveyborough","addressState":"Rhode Island","addressZip":"74130","dept_id":83431},{"job_title":"International Division Assistant","supervisor":"Nienow","first_name":"Jaylan","last_name":"Morissette","work_email":"Marley88@yahoo.com","addressStreet":"84135 Eichmann Park","addressCity":"Loweberg","addressState":"Montana","addressZip":"78544","dept_id":75220},{"job_title":"Investor Program Representative","supervisor":"Zboncak","first_name":"Vicente","last_name":"Howe","work_email":"Patrick.Pagac@hotmail.com","addressStreet":"035 Herman Prairie","addressCity":"Rohanville","addressState":"Alabama","addressZip":"71169-6978","dept_id":62808},{"job_title":"Forward Division Representative","supervisor":"Schultz","first_name":"Madisen","last_name":"Gulgowski","work_email":"Dustin.Wintheiser37@hotmail.com","addressStreet":"769 Alejandrin Avenue","addressCity":"Elisashire","addressState":"Kansas","addressZip":"43698-0713","dept_id":74557},{"job_title":"Principal Directives Administrator","supervisor":"Bergstrom","first_name":"Tressie","last_name":"Stehr","work_email":"Vincenza35@yahoo.com","addressStreet":"3392 Claudine Ridge","addressCity":"MacGyverland","addressState":"Alabama","addressZip":"94064-0962","dept_id":9354},{"job_title":"Customer Directives Manager","supervisor":"Brown","first_name":"Price","last_name":"Erdman","work_email":"Rosalind.Flatley45@hotmail.com","addressStreet":"0180 Gina View","addressCity":"North Virginiehaven","addressState":"Connecticut","addressZip":"31953-7477","dept_id":45728},{"job_title":"Central Program Associate","supervisor":"Funk","first_name":"Geraldine","last_name":"Weissnat","work_email":"Nadia16@gmail.com","addressStreet":"31644 Delia Junctions","addressCity":"Adelbertview","addressState":"Washington","addressZip":"24715","dept_id":60437},{"job_title":"Future Brand Liaison","supervisor":"Gerlach","first_name":"Carmel","last_name":"Labadie","work_email":"Octavia33@gmail.com","addressStreet":"72023 Padberg Squares","addressCity":"North Eudora","addressState":"Ohio","addressZip":"28272","dept_id":12639},{"job_title":"Direct Functionality Agent","supervisor":"Mante","first_name":"Nicolette","last_name":"Zulauf","work_email":"Elian_Rippin14@hotmail.com","addressStreet":"9164 Gutkowski Vista","addressCity":"Geoffreyfort","addressState":"Idaho","addressZip":"40288","dept_id":99644},{"job_title":"Central Functionality Coordinator","supervisor":"Miller","first_name":"Ethelyn","last_name":"Wintheiser","work_email":"Ramona16@gmail.com","addressStreet":"02956 Tiana Port","addressCity":"Ryanshire","addressState":"Tennessee","addressZip":"98733-6708","dept_id":6182}]